<?xml version="1.0" encoding="UTF-8"?>
<GenRun Id="synth_1" LaunchPart="xc7a100tcsg324-1" LaunchTime="1457697926">
  <File Type="RDS-DCP" Name="top_lvl.dcp"/>
  <File Type="RUN-CONSTRS" Name="$PDATADIR/runs/synth_1/constrs_in.xml"/>
  <File Type="RDS-UTIL-PB" Name="top_lvl_utilization_synth.pb"/>
  <File Type="RUN-SRCS" Name="$PDATADIR/runs/synth_1/sources.xml"/>
  <File Type="RDS-PROPCONSTRS" Name="top_lvl_drc_synth.rpt"/>
  <File Type="PA-TCL" Name="top_lvl.tcl"/>
  <File Type="RUN-STRAT" Name="$PDATADIR/runs/synth_1/synth_1.psg"/>
  <File Type="RDS-RDS" Name="top_lvl.vds"/>
  <File Type="RDS-UTIL" Name="top_lvl_utilization_synth.rpt"/>
  <File Type="VDS-TIMINGSUMMARY" Name="top_lvl_timing_summary_synth.rpt"/>
  <File Type="VDS-TIMING-PB" Name="top_lvl_timing_summary_synth.pb"/>
  <FileSet Name="sources" Type="DesignSrcs" RelSrcDir="$PSRCDIR/sources_1">
    <Filter Type="Srcs"/>
    <File Path="$PSRCDIR/sources_1/new/ALU_mock.vhd">
      <FileInfo>
        <Attr Name="UsedIn" Val="synthesis"/>
        <Attr Name="UsedIn" Val="simulation"/>
      </FileInfo>
    </File>
    <File Path="$PSRCDIR/sources_1/new/program_memory.vhd">
      <FileInfo>
        <Attr Name="UsedIn" Val="synthesis"/>
        <Attr Name="UsedIn" Val="simulation"/>
      </FileInfo>
    </File>
    <File Path="$PSRCDIR/sources_1/bd/programator/programator.bd">
      <FileInfo>
        <Attr Name="UsedIn" Val="synthesis"/>
        <Attr Name="UsedIn" Val="implementation"/>
        <Attr Name="UsedIn" Val="simulation"/>
      </FileInfo>
    </File>
    <File Path="$PSRCDIR/sources_1/new/marker_memory.vhd">
      <FileInfo>
        <Attr Name="UsedIn" Val="synthesis"/>
        <Attr Name="UsedIn" Val="simulation"/>
      </FileInfo>
    </File>
    <File Path="$PSRCDIR/sources_1/new/IO_controller.vhd">
      <FileInfo>
        <Attr Name="UsedIn" Val="synthesis"/>
        <Attr Name="UsedIn" Val="simulation"/>
      </FileInfo>
    </File>
    <File Path="$PSRCDIR/sources_1/new/DIO_module_mock.vhd">
      <FileInfo>
        <Attr Name="UsedIn" Val="synthesis"/>
        <Attr Name="UsedIn" Val="simulation"/>
      </FileInfo>
    </File>
    <File Path="$PSRCDIR/sources_1/new/CPU.vhd">
      <FileInfo>
        <Attr Name="UsedIn" Val="synthesis"/>
        <Attr Name="UsedIn" Val="simulation"/>
      </FileInfo>
    </File>
    <File Path="$PSRCDIR/sources_1/new/7seg_driver.vhd">
      <FileInfo>
        <Attr Name="UsedIn" Val="synthesis"/>
        <Attr Name="UsedIn" Val="simulation"/>
      </FileInfo>
    </File>
    <File Path="$PSRCDIR/sources_1/new/top_lvl.vhd">
      <FileInfo>
        <Attr Name="UsedIn" Val="synthesis"/>
        <Attr Name="UsedIn" Val="simulation"/>
      </FileInfo>
    </File>
    <File Path="$PSRCDIR/sources_1/bd/programator/ip/programator_mig_7series_0_0/board.prj">
      <FileInfo>
        <Attr Name="UsedIn" Val="synthesis"/>
      </FileInfo>
    </File>
    <File Path="$PSDKDIR/programator/Debug/programator.elf">
      <FileInfo>
        <Attr Name="UsedIn" Val="implementation"/>
        <Attr Name="ScopedToRef" Val="programator"/>
        <Attr Name="ScopedToCell" Val="microblaze_0"/>
        <Attr Name="IsVisible" Val="1"/>
      </FileInfo>
    </File>
    <Config>
      <Option Name="DesignMode" Val="RTL"/>
      <Option Name="TopModule" Val="top_lvl"/>
      <Option Name="TopAutoSet" Val="TRUE"/>
    </Config>
  </FileSet>
  <FileSet Name="constrs_in" Type="Constrs" RelSrcDir="$PSRCDIR/constrs_1">
    <Filter Type="Constrs"/>
    <File Path="$PSRCDIR/constrs_1/imports/Downloads/Nexys4DDR_Master.xdc">
      <FileInfo>
        <Attr Name="ImportPath" Val="$PPRDIR/../../../../../Downloads/Nexys4DDR_Master.xdc"/>
        <Attr Name="ImportTime" Val="1418224684"/>
        <Attr Name="UsedIn" Val="synthesis"/>
        <Attr Name="UsedIn" Val="implementation"/>
      </FileInfo>
    </File>
    <Config>
      <Option Name="ConstrsType" Val="XDC"/>
    </Config>
  </FileSet>
  <Strategy Version="1" Minor="2">
    <StratHandle Name="Vivado Synthesis Defaults" Flow="Vivado Synthesis 2015"/>
    <Step Id="synth_design"/>
  </Strategy>
</GenRun>
